temscript/__init__.py
temscript/_com.py
temscript/_instrument_com.py
temscript/_instrument_stubs.py
temscript/base_microscope.py
temscript/enums.py
temscript/instrument.py
temscript/marshall.py
temscript/microscope.py
temscript/null_microscope.py
temscript/remote_microscope.py
temscript/server.py
temscript/version.py
temscript-2.1.0.dist-info/LICENSE
temscript-2.1.0.dist-info/METADATA
temscript-2.1.0.dist-info/WHEEL
temscript-2.1.0.dist-info/entry_points.txt
temscript-2.1.0.dist-info/top_level.txt
temscript-2.1.0.dist-info/RECORD
