Metadata-Version: 2.2
Name: temscript
Version: 2.1.0
Summary: TEM Scripting adapter for FEI microscopes
Home-page: https://github.com/niermann/temscript
Author: Tore Niermann
Author-email: tore.niermann@tu-berlin.de
License: BSD 3-Clause License
Project-URL: Source, https://github.com/niermann/temscript
Project-URL: Documentation, https://temscript.readthedocs.io/
Platform: any
Classifier: Development Status :: 5 - Production/Stable
Classifier: Intended Audience :: Science/Research
Classifier: Intended Audience :: Developers
Classifier: Operating System :: OS Independent
Classifier: Programming Language :: Python :: 3
Classifier: Topic :: Scientific/Engineering
Classifier: Topic :: Software Development :: Libraries
Classifier: License :: OSI Approved :: BSD License
Classifier: Operating System :: OS Independent
Requires-Python: >=3.4
License-File: LICENSE
Requires-Dist: numpy
Dynamic: author
Dynamic: author-email
Dynamic: classifier
Dynamic: description
Dynamic: description-content-type
Dynamic: home-page
Dynamic: license
Dynamic: platform
Dynamic: project-url
Dynamic: requires-dist
Dynamic: requires-python
Dynamic: summary
